wbportfolio/__init__.py
wbportfolio/apps.py
wbportfolio/dynamic_preferences_registry.py
wbportfolio/permissions.py
wbportfolio/preferences.py
wbportfolio/tasks.py
wbportfolio/urls.py
wbportfolio/utils.py
wbportfolio/admin/__init__.py
wbportfolio/admin/asset.py
wbportfolio/admin/custodians.py
wbportfolio/admin/portfolio.py
wbportfolio/admin/portfolio_relationships.py
wbportfolio/admin/product_groups.py
wbportfolio/admin/products.py
wbportfolio/admin/reconciliations.py
wbportfolio/admin/registers.py
wbportfolio/admin/roles.py
wbportfolio/admin/synchronization/__init__.py
wbportfolio/admin/synchronization/admin.py
wbportfolio/admin/synchronization/portfolio_synchronization.py
wbportfolio/admin/synchronization/price_computation.py
wbportfolio/admin/transactions/__init__.py
wbportfolio/admin/transactions/claim.py
wbportfolio/admin/transactions/dividends.py
wbportfolio/admin/transactions/fees.py
wbportfolio/admin/transactions/trades.py
wbportfolio/admin/transactions/transactions.py
wbportfolio/analysis/__init__.py
wbportfolio/analysis/claims.py
wbportfolio/contrib/__init__.py
wbportfolio/contrib/company_portfolio/__init__.py
wbportfolio/contrib/company_portfolio/admin.py
wbportfolio/contrib/company_portfolio/apps.py
wbportfolio/contrib/company_portfolio/constants.py
wbportfolio/contrib/company_portfolio/dynamic_preferences_registry.py
wbportfolio/contrib/company_portfolio/factories.py
wbportfolio/contrib/company_portfolio/filters.py
wbportfolio/contrib/company_portfolio/management.py
wbportfolio/contrib/company_portfolio/models.py
wbportfolio/contrib/company_portfolio/scripts.py
wbportfolio/contrib/company_portfolio/serializers.py
wbportfolio/contrib/company_portfolio/tasks.py
wbportfolio/contrib/company_portfolio/urls.py
wbportfolio/contrib/company_portfolio/viewsets.py
wbportfolio/contrib/company_portfolio/configs/__init__.py
wbportfolio/contrib/company_portfolio/configs/display.py
wbportfolio/contrib/company_portfolio/configs/endpoints.py
wbportfolio-2.2.6.dist-info/METADATA
wbportfolio-2.2.6.dist-info/WHEEL
wbportfolio-2.2.6.dist-info/licenses/LICENSE
wbportfolio-2.2.6.dist-info/RECORD
