Metadata-Version: 2.4
Name: wbportfolio
Version: 2.2.6
Author-email: Christopher Wittlinger <c.wittlinger@stainly.com>
License-File: LICENSE
Requires-Dist: cryptography==3.4.*
Requires-Dist: dateparser==1.*
Requires-Dist: django-storages==1.14.*
Requires-Dist: fuzzywuzzy==0.*
Requires-Dist: jinjasql2==0.1.*
Requires-Dist: msoffcrypto-tool==4.10.*
Requires-Dist: python-levenshtein==0.*
Requires-Dist: reportlab==3.*
Requires-Dist: scipy>=1
Requires-Dist: wbcompliance
Requires-Dist: wbcore
Requires-Dist: wbcrm
Requires-Dist: wbfdm
Requires-Dist: wbnews
Requires-Dist: weasyprint==57.*
Requires-Dist: xlrd==2.*
Requires-Dist: xlsxwriter==3.*
